datawhisk/__init__.py
datawhisk/exceptions.py
datawhisk/utils.py
datawhisk/version.py
datawhisk/analytical/__init__.py
datawhisk/analytical/correlation_analyzer.py
datawhisk/analytical/eda_reporter.py
datawhisk/analytical/memory_optimizer.py
datawhisk-1.0.3.dist-info/licenses/LICENSE
datawhisk-1.0.3.dist-info/METADATA
datawhisk-1.0.3.dist-info/WHEEL
datawhisk-1.0.3.dist-info/top_level.txt
datawhisk-1.0.3.dist-info/RECORD
