Metadata-Version: 2.4
Name: datawhisk
Version: 1.0.3
Summary: A lightweight, practical utility library for data scientists and ML engineers
Author-email: RamMohan Reddy K <ramku3639@gmail.com>
Maintainer-email: RamMohan Reddy K <ramku3639@gmail.com>
License: MIT
Project-URL: Homepage, https://github.com/Ramku3639/datawhisk
Project-URL: Documentation, https://github.com/Ramku3639/datawhisk/blob/main/docs/README.md
Project-URL: Repository, https://github.com/Ramku3639/datawhisk
Project-URL: Bug Tracker, https://github.com/Ramku3639/datawhisk/issues
Project-URL: Changelog, https://github.com/Ramku3639/datawhisk/blob/main/CHANGELOG.md
Keywords: data-science,machine-learning,data-analysis,pandas,utilities,eda,correlation,memory-optimization
Classifier: Development Status :: 3 - Alpha
Classifier: Intended Audience :: Developers
Classifier: Intended Audience :: Science/Research
Classifier: License :: OSI Approved :: MIT License
Classifier: Programming Language :: Python :: 3
Classifier: Programming Language :: Python :: 3.8
Classifier: Programming Language :: Python :: 3.9
Classifier: Programming Language :: Python :: 3.10
Classifier: Programming Language :: Python :: 3.11
Classifier: Programming Language :: Python :: 3.12
Classifier: Programming Language :: Python :: 3.13
Classifier: Topic :: Scientific/Engineering
Classifier: Topic :: Software Development :: Libraries :: Python Modules
Requires-Python: >=3.8
License-File: LICENSE
Requires-Dist: numpy>=1.20.0
Requires-Dist: pandas>=1.3.0
Requires-Dist: scipy>=1.7.0
Provides-Extra: viz
Requires-Dist: matplotlib>=3.3.0; extra == "viz"
Requires-Dist: seaborn>=0.11.0; extra == "viz"
Provides-Extra: dev
Requires-Dist: pytest>=7.0.0; extra == "dev"
Requires-Dist: pytest-cov>=4.0.0; extra == "dev"
Requires-Dist: black>=22.0.0; extra == "dev"
Requires-Dist: flake8>=5.0.0; extra == "dev"
Requires-Dist: mypy>=0.990; extra == "dev"
Requires-Dist: pylint>=2.15.0; extra == "dev"
Requires-Dist: isort>=5.10.0; extra == "dev"
Provides-Extra: docs
Requires-Dist: sphinx>=5.0.0; extra == "docs"
Requires-Dist: sphinx-rtd-theme>=1.0.0; extra == "docs"
Requires-Dist: nbsphinx>=0.8.0; extra == "docs"
Requires-Dist: jupyter>=1.0.0; extra == "docs"
Provides-Extra: all
Requires-Dist: datawhisk[dev,docs,viz]; extra == "all"
Dynamic: license-file
